{
    "summoner":{
        "move_range" : 5,
        "health" : 10,
        "action_points" : 6,
        "reach" : 1,
        "absorption": 3,
        "scene_name":"summoner",
        "type":"player",
        "blocking":true
    },
    "masked_orc" : {
        "move_range" : 5,
        "health" : 7,
        "action_points" : 6,
        "reach" : 1,
        "absorption": 3,
        "scene_name":"masked_orc",
        "type":"enemy",
        "blocking":true
    },
    "slime" : {
        "move_range" : 5,
        "health" : 5,
        "action_points" : 6,
        "reach" : 1,
        "absorption": 3,
        "scene_name":"slime",
        "type":"enemy",
        "blocking":true
    }
}